sslouvain-0.1.1.dist-info/LICENSE
sslouvain-0.1.1.dist-info/WHEEL
sslouvain-0.1.1.dist-info/top_level.txt
sslouvain-0.1.1.dist-info/METADATA
sslouvain-0.1.1.dist-info/RECORD
sslouvain.libs/libigraph-8fc433fa.so.0.0.0
sslouvain.libs/libgmp-afec2dd4.so.10.2.0
sslouvain.libs/liblzma-004595ca.so.5.2.2
sslouvain.libs/libxml2-3998bec4.so.2.9.1
sslouvain/Optimiser.py
sslouvain/_version.py
sslouvain/_c_louvain.cpython-311-x86_64-linux-gnu.so
sslouvain/VertexPartition.py
sslouvain/functions.py
sslouvain/__init__.py
