Metadata-Version: 2.1
Name: sslouvain
Version: 0.1.1
Summary: ssLouvain extends the popular Louvain package.
Home-page: https://github.com/dakota-hawkins/sslouvain
Author: V.A. Traag + Dakota Hawkins
Author-email: dyh0110@bu.edu
License: GPLv3+
Platform: UNKNOWN
Classifier: Development Status :: 4 - Beta
Classifier: Environment :: Console
Classifier: Intended Audience :: End Users/Desktop
Classifier: Intended Audience :: Developers
Classifier: Intended Audience :: Science/Research
Classifier: License :: OSI Approved :: GNU General Public License v3 or later (GPLv3+)
Classifier: Operating System :: MacOS :: MacOS X
Classifier: Operating System :: Microsoft :: Windows
Classifier: Operating System :: POSIX
Classifier: Programming Language :: Python
Classifier: Programming Language :: C++
Classifier: Topic :: Scientific/Engineering :: Mathematics
Classifier: Topic :: Scientific/Engineering :: Information Analysis
Classifier: Topic :: Sociology
Classifier: Topic :: Scientific/Engineering :: Bio-Informatics
Provides: sslouvain
License-File: LICENSE
Requires-Dist: python-igraph (>=0.7.1)
